promise_keeper.py
promise_keeper-1.0.0.dist-info/LICENSE
promise_keeper-1.0.0.dist-info/METADATA
promise_keeper-1.0.0.dist-info/WHEEL
promise_keeper-1.0.0.dist-info/top_level.txt
promise_keeper-1.0.0.dist-info/RECORD
