Metadata-Version: 2.1
Name: promise-keeper
Version: 1.0.0
Summary: A simple async processing helper
Author-email: Steve Brettschneider <steve@bluehousefamily.com>, Rémi Desgrange <remi.desgrange@camptocamp.com>
License: GNU AFFERO GENERAL PUBLIC LICENSE
Project-URL: Homepage, https://github.com/brettschneider/python_promise_keeper
Project-URL: Bug Tracker, https://github.com/brettschneider/python_promise_keeper/issues
Classifier: Programming Language :: Python :: 3
Classifier: License :: OSI Approved :: GNU General Public License v3 or later (GPLv3+)
Classifier: Operating System :: OS Independent
Requires-Python: >=3.8
License-File: LICENSE
